flask_jeroboam/__init__.py
flask_jeroboam/_config.py
flask_jeroboam/_constants.py
flask_jeroboam/_inboundhandler.py
flask_jeroboam/_logger.py
flask_jeroboam/_outboundhandler.py
flask_jeroboam/_utils.py
flask_jeroboam/blueprint.py
flask_jeroboam/blueprint.pyi
flask_jeroboam/datastructures.py
flask_jeroboam/exceptions.py
flask_jeroboam/jeroboam.py
flask_jeroboam/jeroboam.pyi
flask_jeroboam/models.py
flask_jeroboam/openapi/__init__.py
flask_jeroboam/openapi/_utils.py
flask_jeroboam/openapi/blueprint.py
flask_jeroboam/openapi/builder.py
flask_jeroboam/openapi/models/openapi.py
flask_jeroboam/openapi/models/ui_context.py
flask_jeroboam/openapi/templates/swagger-ui.jinja
flask_jeroboam/py.typed
flask_jeroboam/responses.py
flask_jeroboam/rule.py
flask_jeroboam/scaffold.py
flask_jeroboam/scaffold.pyi
flask_jeroboam/typing.py
flask_jeroboam/view.py
flask_jeroboam/view_arguments/__init__.py
flask_jeroboam/view_arguments/_utils.py
flask_jeroboam/view_arguments/arguments.py
flask_jeroboam/view_arguments/functions.py
flask_jeroboam/view_arguments/functions.pyi
flask_jeroboam/view_arguments/solved.py
flask_jeroboam/wrapper.py
flask_jeroboam/wrapper.pyi
flask_jeroboam-0.1.1.dist-info/LICENSE
flask_jeroboam-0.1.1.dist-info/METADATA
flask_jeroboam-0.1.1.dist-info/WHEEL
flask_jeroboam-0.1.1.dist-info/RECORD
