Metadata-Version: 2.3
Name: flask-jeroboam
Version: 0.1.1
Summary: A Flask extension, inspired by FastAPI that uses Pydantic to provide easy-to-configure data validation for request parsing and response serialization.
License: MIT
Keywords: flask,pydantic,validation,serialization
Author: Jean-Christophe Bianic
Author-email: jc.bianic@gmail.com
Requires-Python: >=3.9
Classifier: Development Status :: 4 - Beta
Classifier: Environment :: Web Environment
Classifier: Framework :: Flask
Classifier: Framework :: Pydantic
Classifier: Intended Audience :: Developers
Classifier: License :: OSI Approved :: MIT License
Classifier: Operating System :: OS Independent
Classifier: Programming Language :: Python
Classifier: Programming Language :: Python :: 3
Classifier: Programming Language :: Python :: 3.10
Classifier: Programming Language :: Python :: 3.11
Classifier: Programming Language :: Python :: 3.12
Classifier: Programming Language :: Python :: 3.13
Classifier: Programming Language :: Python :: 3 :: Only
Classifier: Programming Language :: Python :: 3.9
Classifier: Topic :: Internet
Classifier: Topic :: Internet :: WWW/HTTP
Classifier: Topic :: Internet :: WWW/HTTP :: HTTP Servers
Classifier: Topic :: Software Development
Classifier: Topic :: Software Development :: Libraries :: Application Frameworks
Classifier: Typing :: Typed
Requires-Dist: Flask (>=3.1.0,<4.0.0)
Requires-Dist: pydantic1 (>=1.10.3,<2.0.0)
Requires-Dist: wheel (>=0.45.1,<0.46.0)
Project-URL: Documentation, https://flask-jeroboam.readthedocs.io
Project-URL: Homepage, https://github.com/jcbianic/flask-jeroboam
Project-URL: Repository, https://github.com/jcbianic/flask-jeroboam
